pyconfita/__init__.py
pyconfita/logging_interface.py
pyconfita/pyconfita.py
pyconfita/backend/__init__.py
pyconfita/backend/backend.py
pyconfita/backend/dict/__init__.py
pyconfita/backend/dict/dict.py
pyconfita/backend/environment/__init__.py
pyconfita/backend/environment/environment.py
pyconfita/backend/file/__init__.py
pyconfita/backend/file/file.py
pyconfita/backend/string/__init__.py
pyconfita/backend/string/string.py
pyconfita/backend/vault/__init__.py
pyconfita/backend/vault/vault.py
pyconfita-1.1.1.dist-info/LICENSE
pyconfita-1.1.1.dist-info/METADATA
pyconfita-1.1.1.dist-info/WHEEL
pyconfita-1.1.1.dist-info/top_level.txt
pyconfita-1.1.1.dist-info/RECORD
