Metadata-Version: 2.1
Name: pyconfita
Version: 1.1.1
Summary: PyConfita: Confita-like library for Python
Home-page: https://github.com/m-letourneur/pyconfita.git
Classifier: Programming Language :: Python :: 3
Classifier: Operating System :: OS Independent
Requires-Python: >=3.8, <3.12
License-File: LICENSE
Requires-Dist: hvac ==0.11.2
Requires-Dist: cacheout ==0.14.1
Requires-Dist: pyYaml
